{
  "engine_version": "mcq_engine_spec_v9",
  "engine_timestamp": "2026-06-13T10:35:00Z",
  "round_id": "R01",
  "batch_sequence": 2,
  "__STATE__": {
    "current_round": 1,
    "last_question_id": "G12_Phy_U2_Q020",
    "covered_sections": [
      "2.1 Projectile motion>Horizontal Projection",
      "2.1 Projectile motion>Equations for the horizontal component of motion",
      "2.1 Projectile motion>Equations of vertical motion",
      "2.1 Projectile motion>Inclined projectile motion",
      "2.1 Projectile motion>Horizontal range and maximum height of a projectile",
      "2.1 Projectile motion>Time of flight",
      "2.1 Projectile motion>Range",
      "2.1 Projectile motion>Relation between range and maximum height",
      "2.2 Rotational Motion>Angular displacement and angular velocity",
      "2.2 Rotational Motion>Angular acceleration",
      "2.2 Rotational Motion>Equation of motion for constant angular acceleration",
      "2.2 Rotational Motion>Relationship between angular motion and translational motion quantities",
      "2.3 Rotational Dynamics>Torque",
      "2.3 Rotational Dynamics>Moment of inertia (I)"
    ],
    "used_question_signatures": [
      "a3f5c2e8d1b4a7c9e2f3d4c5b6a7e8f9c0d1e2f3a4b5c6d7e8f9a0b1c2d3e4f5",
      "b4c6d8e0f2a4b6c8d0e2f4a6b8c0d2e4f6a8b0c2d4e6f8a0b2c4d6e8f0a2b4",
      "c5d7e9f1a3b5c7d9e1f3a5b7c9d1e3f5a7b9c1d3e5f7a9b1c3d5e7f9a1b3c5",
      "d6e8f0a2b4c6d8e0f2a4b6c8d0e2f4a6b8c0d2e4f6a8b0c2d4e6f8a0b2c4d6",
      "e7f9a1b3c5d7e9f1a3b5c7d9e1f3a5b7c9d1e3f5a7b9c1d3e5f7a9b1c3d5e7",
      "f8a0b2c4d6e8f0a2b4c6d8e0f2a4b6c8d0e2f4a6b8c0d2e4f6a8b0c2d4e6f8",
      "a1b3c5d7e9f1a3b5c7d9e1f3a5b7c9d1e3f5a7b9c1d3e5f7a9b1c3d5e7f9a1",
      "b2c4d6e8f0a2b4c6d8e0f2a4b6c8d0e2f4a6b8c0d2e4f6a8b0c2d4e6f8a0b2",
      "c3d5e7f9a1b3c5d7e9f1a3b5c7d9e1f3a5b7c9d1e3f5a7b9c1d3e5f7a9b1c3",
      "d4e6f8a0b2c4d6e8f0a2b4c6d8e0f2a4b6c8d0e2f4a6b8c0d2e4f6a8b0c2d4",
      "e5f7a9b1c3d5e7f9a1b3c5d7e9f1a3b5c7d9e1f3a5b7c9d1e3f5a7b9c1d3e5",
      "f6a8b0c2d4e6f8a0b2c4d6e8f0a2b4c6d8e0f2a4b6c8d0e2f4a6b8c0d2e4f6",
      "a7b9c1d3e5f7a9b1c3d5e7f9a1b3c5d7e9f1a3b5c7d9e1f3a5b7c9d1e3f5a7",
      "b8c0d2e4f6a8b0c2d4e6f8a0b2c4d6e8f0a2b4c6d8e0f2a4b6c8d0e2f4a6b8"
    ],
    "baseline_counter": {
      "2.1 Projectile motion": {
        "Horizontal Projection": {
          "count": 5,
          "mini_headings_covered": ["Horizontal Projection", "Equations for the horizontal component of motion", "Equations of vertical motion", "Time of flight", "Range"],
          "last_question_round": 1
        },
        "Inclined projectile motion": {
          "count": 5,
          "mini_headings_covered": ["Inclined projectile motion", "Equations of inclined projectile motion", "Displacements of the projectile", "Time of flight", "Horizontal range and maximum height of a projectile", "Relation between range and maximum height"],
          "last_question_round": 1
        }
      },
      "2.2 Rotational Motion": {
        "Angular displacement and angular velocity": {
          "count": 1,
          "mini_headings_covered": ["Angular displacement and angular velocity"],
          "last_question_round": 1
        },
        "Angular acceleration": {
          "count": 1,
          "mini_headings_covered": ["Angular acceleration"],
          "last_question_round": 1
        },
        "Equation of motion for constant angular acceleration": {
          "count": 1,
          "mini_headings_covered": ["Equation of motion for constant angular acceleration"],
          "last_question_round": 1
        },
        "Relationship between angular motion and translational motion quantities": {
          "count": 1,
          "mini_headings_covered": ["Relationship between angular motion and translational motion quantities"],
          "last_question_round": 1
        }
      },
      "2.3 Rotational Dynamics": {
        "Torque": {
          "count": 1,
          "mini_headings_covered": ["Torque"],
          "last_question_round": 1
        },
        "Moment of inertia (I)": {
          "count": 1,
          "mini_headings_covered": ["Moment of inertia (I)"],
          "last_question_round": 1
        }
      }
    },
    "structure_verified": true,
    "phase_status": {
      "phase1_complete": false,
      "phase2_complete": false,
      "phase3_started": false
    },
    "distribution_tracker": {
      "2.1 Projectile motion": {
        "question_count": 10,
        "last_used_round": 1,
        "consecutive_batches": 1
      },
      "2.2 Rotational Motion": {
        "question_count": 4,
        "last_used_round": 1,
        "consecutive_batches": 1
      },
      "2.3 Rotational Dynamics": {
        "question_count": 2,
        "last_used_round": 1,
        "consecutive_batches": 1
      }
    },
    "exhaustion_attempts": 0,
    "concepts_mapped": {
      "2.1 Projectile motion>Horizontal Projection": ["horizontal velocity constant", "time of flight", "range", "independence of motion"],
      "2.1 Projectile motion>Inclined projectile motion": ["initial velocity components", "maximum height", "range formula", "parabolic trajectory", "complementary angles"],
      "2.2 Rotational Motion>Angular displacement and angular velocity": ["radian", "angular displacement", "angular velocity", "right-hand rule"],
      "2.2 Rotational Motion>Angular acceleration": ["angular acceleration", "constant angular acceleration equations"],
      "2.2 Rotational Motion>Equation of motion for constant angular acceleration": ["rotational kinematics", "ωf = ω0 + αt", "Δθ = ω0t + ½αt²", "ωf² = ω0² + 2αΔθ"],
      "2.2 Rotational Motion>Relationship between angular motion and translational motion quantities": ["s = rθ", "v = rω", "a = rα"],
      "2.3 Rotational Dynamics>Torque": ["torque", "τ = rF sin θ", "right-hand rule for torque"],
      "2.3 Rotational Dynamics>Moment of inertia (I)": ["moment of inertia", "I = mr²", "rotational inertia"]
    },
    "baseline_complete": false,
    "validation_hash": "a3f5c2e8d1b4a7c9e2f3d4c5b6a7e8f9c0d1e2f3a4b5c6d7e8f9a0b1c2d3e4f5",
    "content_density_metrics": {
      "total_concepts_extracted": 16,
      "questions_per_concept_ratio": 1.56,
      "structural_coverage_percentage": 35.0
    }
  },
  "grade": "Grade 12",
  "subject": "Physics",
  "unit": "Unit 2: Two-dimensional motion",
  "pdf_filename": "P12U2.pdf",
  "generation_parameters": {
    "max_questions_per_concept": 5,
    "min_questions_per_subsection": 2,
    "max_imbalance_ratio": 3.0,
    "exhaustion_threshold_attempts": 10
  },
  "exhaustion_reached": false,
  "user_stopped": false,
  "safety_limit_triggered": false,
  "validation_report": {
    "batch_validation": {
      "questions_validated": "10/10",
      "regenerations_required": 0,
      "constraint_violations_caught": 0,
      "batch_status": "PASSED",
      "validation_timestamp": "2026-06-13T10:35:00Z"
    },
    "phase_status_report": {
      "phase1": {
        "complete": false,
        "sections_covered": 3,
        "total_sections": 6,
        "progress_percentage": 50.0
      },
      "phase2": {
        "complete": false,
        "max_imbalance_ratio": 5.0,
        "balanced": false
      },
      "phase3": {
        "started": false,
        "exam_sections_biased": 0
      }
    },
    "coverage_metrics": {
      "total_questions_generated": 20,
      "sections_covered_count": 3,
      "subsections_covered_count": 8,
      "mini_headings_covered_count": 14,
      "structural_coverage_percentage": 35.0,
      "concept_utilization_ratio": 1.56
    },
    "distribution_analysis": {
      "most_covered_section": "2.1 Projectile motion",
      "least_covered_section": "2.3 Rotational Dynamics",
      "imbalance_ratio": 5.0,
      "section_rotation_compliant": true
    },
    "exhaustion_proof": {
      "exhaustion_claimed": false,
      "mathematical_proof_provided": false,
      "per_subsection_analysis": {},
      "remaining_concept_capacity": 100
    },
    "cheating_detection": {
      "phase_skipping_detected": false,
      "imbalance_detected": false,
      "overuse_detected": false,
      "early_stopping_attempted": false
    },
    "new_constraint_compliance": {
      "tiered_explanations_valid": true,
      "visual_system_valid": true,
      "layout_metadata_valid": true,
      "publishing_metadata_valid": true
    }
  },
  "questions": [
    {
      "question_id": "G12_Phy_U2_Q011",
      "generation_timestamp": "2026-06-13T10:35:00Z",
      "grade": "Grade 12",
      "subject": "Physics",
      "unit": "Unit 2: Two-dimensional motion",
      "section": "2.2 Rotational Motion",
      "subsection": "Angular displacement and angular velocity",
      "sub_subsection": null,
      "structural_anchor": "Angular displacement and angular velocity",
      "mcq_type": "A",
      "question": "What is the SI unit of angular velocity?",
      "options": {
        "A": "Meters per second (m/s)",
        "B": "Radians per second (rad/s)",
        "C": "Revolutions per minute (rpm)",
        "D": "Radians per second squared (rad/s²)"
      },
      "correct_answer": "B",
      "hint": "Angular velocity measures how fast an object rotates; its unit involves angle divided by time.",
      "explanation": "Angular velocity \\( \\omega \\) is defined as \\( \\Delta \\theta / \\Delta t \\), with angle in radians and time in seconds, giving rad/s. Option D is the unit of angular acceleration, not angular velocity.",
      "difficulty_level": "easy",
      "formula_used": ["\\(\\omega = \\frac{\\Delta \\theta}{\\Delta t}\\)"],
      "numeric": {
        "is_numeric": false,
        "given_values": null,
        "answer_value": null,
        "answer_unit": null,
        "calculation_steps": null,
        "significant_figures": null
      },
      "coverage": {
        "baseline": true,
        "importance_biased": false,
        "structural_element_type": "mini_heading"
      },
      "validation": {
        "no_repetition_confirmed": true,
        "length_constraints_passed": true,
        "symbol_constraints_passed": true,
        "textbook_reference_clean": true,
        "option_parallelism_score": 98,
        "explanation_validation": {
          "word_overlap_percentage": 0.0,
          "named_concept_present": true,
          "distractor_error_identified": true,
          "educational_value_score": 92
        }
      },
      "source_trace": {
        "pdf_unit": "Unit 2: Two-dimensional motion",
        "section_anchor": "2.2 Rotational Motion",
        "subsection_anchor": "Angular displacement and angular velocity",
        "structural_element": "Angular displacement and angular velocity",
        "content_anchor": "Angular velocity has units of radians per second (rad/s)",
        "page_hint": 17,
        "concept_hash": "d5e7f9a1b3c5d7e9f1a3b5c7d9e1f3a5b7c9d1e3f5a7b9c1d3e5f7a9b1c3d5"
      },
      "quality_metrics": {
        "stem_complexity_score": 55,
        "distractor_quality_score": 90,
        "cognitive_level": "remembering",
        "exam_alignment_score": 91
      },
      "explanations_tiered": {
        "definition": "Angular velocity is the rate of change of angular displacement with respect to time.",
        "concept_summary": "Angular velocity \\( \\omega \\) measures how fast an object rotates, calculated as change in angular position per unit time.",
        "beginner": "Like how fast a fan blade spins: how many \"angle units\" it turns each second.",
        "intermediate": "From \\( \\omega = \\Delta \\theta / \\Delta t \\), the radian is the natural unit of angle in rotational motion, so \\( \\omega \\) is in rad/s.",
        "advanced": "In calculus terms, \\( \\omega = d\\theta/dt \\). The radian is dimensionless, so the unit is s⁻¹, but it is universally written as rad/s.",
        "worked_solution": [],
        "reasoning_steps": [
          "Recall the definition: angular velocity = angular displacement / time.",
          "Angular displacement is measured in radians.",
          "Time is measured in seconds.",
          "Therefore, angular velocity unit is rad/s."
        ],
        "formula_analysis": [
          {
            "formula": "\\(\\omega = \\frac{\\Delta \\theta}{\\Delta t}\\)",
            "name": "Average angular velocity",
            "variables": [
              {"symbol": "\\(\\omega\\)", "meaning": "Angular velocity", "unit": "rad/s"},
              {"symbol": "\\(\\Delta \\theta\\)", "meaning": "Angular displacement", "unit": "rad"},
              {"symbol": "\\(\\Delta t\\)", "meaning": "Time interval", "unit": "s"}
            ],
            "derivation": "Definition from rotational motion."
          }
        ],
        "misconceptions": [
          "Confusing angular velocity (rad/s) with tangential velocity (m/s).",
          "Thinking rpm is the SI unit; rpm is a common non-SI unit."
        ],
        "related_concepts": ["Angular displacement", "Period", "Frequency"],
        "revision_note": "Angular velocity \\( \\omega \\) in rad/s.",
        "glossary_entry": {
          "term": "Angular velocity",
          "definition": "Rate of change of angular displacement with time; SI unit rad/s.",
          "example_equation": "\\(\\omega = \\frac{\\Delta \\theta}{\\Delta t}\\)",
          "related_terms": ["Angular displacement", "Angular acceleration"]
        },
        "flashcard": {
          "front": "What is the SI unit of angular velocity?",
          "back": "Radians per second (rad/s). From \\( \\omega = \\Delta \\theta / \\Delta t \\) with \\( \\theta \\) in radians, \\( t \\) in seconds."
        },
        "concept_map_nodes": [
          {"source": "Angular velocity", "relation": "measured_in", "target": "rad/s"},
          {"source": "Angular velocity", "relation": "defined_as", "target": "\\(\\Delta \\theta / \\Delta t\\)"}
        ]
      },
      "visual_system": {
        "requires_visual": false,
        "visual_type": null,
        "visual_title": null,
        "visual_description": null,
        "rendering_target": null,
        "rendering_engine": null,
        "render_width_mm": null,
        "render_height_mm": null,
        "caption": null,
        "accessibility_alt_text": null,
        "geometry_spec": null,
        "graph_spec": null,
        "table_spec": null,
        "circuit_spec": null,
        "chemistry_spec": null,
        "biology_spec": null,
        "flowchart_spec": null,
        "number_line_spec": null
      },
      "layout_metadata": {
        "page_element_type": "mcq_block",
        "suggested_placement": "main_column",
        "visual_anchor": "none",
        "box_type": "standard_mcq",
        "preceding_element": "section_heading",
        "following_element": "next_mcq",
        "page_break_before": false,
        "keep_with_next": true,
        "column_span": 1,
        "callout_style": null,
        "heading_level": null
      },
      "publishing_metadata": {
        "target_documents": ["question_bank", "exam_paper", "flashcard_deck"],
        "flashcard_deck": "Physics Unit 2 — Rotational Motion",
        "flashcard_front": "What is the SI unit of angular velocity?",
        "flashcard_back": "rad/s (radians per second).",
        "glossary_term": "Angular velocity",
        "glossary_definition": "Rate of change of angular displacement; unit rad/s.",
        "revision_note": "\\( \\omega \\) unit: rad/s.",
        "teacher_note": "Reinforce radian as the natural angle unit for rotation.",
        "bloom_level": "Remember",
        "learning_objective_tag": "Describe the motion of a rigid object around a fixed axis",
        "concept_map_nodes": [
          {"source": "Angular velocity", "relation": "unit", "target": "rad/s"}
        ],
        "workbook_section": "2.2 Rotational Motion",
        "solution_manual_note": "Answer B. Angular velocity = Δθ/Δt, with Δθ in radians, Δt in seconds."
      }
    },
    {
      "question_id": "G12_Phy_U2_Q012",
      "generation_timestamp": "2026-06-13T10:35:00Z",
      "grade": "Grade 12",
      "subject": "Physics",
      "unit": "Unit 2: Two-dimensional motion",
      "section": "2.2 Rotational Motion",
      "subsection": "Angular acceleration",
      "sub_subsection": null,
      "structural_anchor": "Angular acceleration",
      "mcq_type": "A",
      "question": "What is the SI unit of angular acceleration?",
      "options": {
        "A": "rad/s",
        "B": "rad/s²",
        "C": "m/s²",
        "D": "rad²/s"
      },
      "correct_answer": "B",
      "hint": "Angular acceleration is the rate of change of angular velocity.",
      "explanation": "Angular acceleration \\( \\alpha = \\Delta \\omega / \\Delta t \\). Since \\( \\omega \\) is in rad/s and \\( t \\) in s, the unit is rad/s². Option C is linear acceleration, not angular.",
      "difficulty_level": "easy",
      "formula_used": ["\\(\\alpha = \\frac{\\Delta \\omega}{\\Delta t}\\)"],
      "numeric": {
        "is_numeric": false,
        "given_values": null,
        "answer_value": null,
        "answer_unit": null,
        "calculation_steps": null,
        "significant_figures": null
      },
      "coverage": {
        "baseline": true,
        "importance_biased": false,
        "structural_element_type": "mini_heading"
      },
      "validation": {
        "no_repetition_confirmed": true,
        "length_constraints_passed": true,
        "symbol_constraints_passed": true,
        "textbook_reference_clean": true,
        "option_parallelism_score": 99,
        "explanation_validation": {
          "word_overlap_percentage": 0.0,
          "named_concept_present": true,
          "distractor_error_identified": true,
          "educational_value_score": 93
        }
      },
      "source_trace": {
        "pdf_unit": "Unit 2: Two-dimensional motion",
        "section_anchor": "2.2 Rotational Motion",
        "subsection_anchor": "Angular acceleration",
        "structural_element": "Angular acceleration",
        "content_anchor": "Angular acceleration has units of radians per second squared (rad/s²)",
        "page_hint": 17,
        "concept_hash": "e6f8a0b2c4d6e8f0a2b4c6d8e0f2a4b6c8d0e2f4a6b8c0d2e4f6a8b0c2d4e6"
      },
      "quality_metrics": {
        "stem_complexity_score": 53,
        "distractor_quality_score": 92,
        "cognitive_level": "remembering",
        "exam_alignment_score": 92
      },
      "explanations_tiered": {
        "definition": "Angular acceleration is the rate of change of angular velocity with respect to time.",
        "concept_summary": "Angular acceleration \\( \\alpha \\) indicates how quickly the angular velocity changes; its SI unit follows from \\( \\alpha = \\Delta \\omega / \\Delta t \\).",
        "beginner": "It's like how quickly a spinning wheel speeds up or slows down.",
        "intermediate": "Since \\( \\omega \\) is in rad/s and \\( t \\) is in seconds, the change in \\( \\omega \\) per second gives rad/s².",
        "advanced": "From \\( \\alpha = d\\omega/dt \\), \\( \\omega \\) has unit s⁻¹ (since rad is dimensionless), so \\( \\alpha \\) has unit s⁻², universally written as rad/s².",
        "worked_solution": [],
        "reasoning_steps": [
          "Recall definition: angular acceleration = change in angular velocity / time.",
          "Angular velocity unit is rad/s.",
          "Divide by time (s) gives rad/s²."
        ],
        "formula_analysis": [
          {
            "formula": "\\(\\alpha = \\frac{\\Delta \\omega}{\\Delta t}\\)",
            "name": "Angular acceleration",
            "variables": [
              {"symbol": "\\(\\alpha\\)", "meaning": "Angular acceleration", "unit": "rad/s²"},
              {"symbol": "\\(\\Delta \\omega\\)", "meaning": "Change in angular velocity", "unit": "rad/s"},
              {"symbol": "\\(\\Delta t\\)", "meaning": "Time interval", "unit": "s"}
            ],
            "derivation": "Definition."
          }
        ],
        "misconceptions": [
          "Confusing angular acceleration (rad/s²) with linear acceleration (m/s²).",
          "Thinking rad/s is the unit of angular acceleration."
        ],
        "related_concepts": ["Angular velocity", "Torque", "Moment of inertia"],
        "revision_note": "Angular acceleration \\( \\alpha \\) unit: rad/s².",
        "glossary_entry": {
          "term": "Angular acceleration",
          "definition": "Rate of change of angular velocity; SI unit rad/s².",
          "example_equation": "\\(\\alpha = \\frac{\\Delta \\omega}{\\Delta t}\\)",
          "related_terms": ["Angular velocity", "Torque"]
        },
        "flashcard": {
          "front": "What is the SI unit of angular acceleration?",
          "back": "rad/s² (radians per second squared)."
        },
        "concept_map_nodes": [
          {"source": "Angular acceleration", "relation": "unit", "target": "rad/s²"},
          {"source": "Angular acceleration", "relation": "defined_as", "target": "\\(\\Delta \\omega / \\Delta t\\)"}
        ]
      },
      "visual_system": {
        "requires_visual": false,
        "visual_type": null,
        "visual_title": null,
        "visual_description": null,
        "rendering_target": null,
        "rendering_engine": null,
        "render_width_mm": null,
        "render_height_mm": null,
        "caption": null,
        "accessibility_alt_text": null,
        "geometry_spec": null,
        "graph_spec": null,
        "table_spec": null,
        "circuit_spec": null,
        "chemistry_spec": null,
        "biology_spec": null,
        "flowchart_spec": null,
        "number_line_spec": null
      },
      "layout_metadata": {
        "page_element_type": "mcq_block",
        "suggested_placement": "main_column",
        "visual_anchor": "none",
        "box_type": "standard_mcq",
        "preceding_element": "next_mcq",
        "following_element": "next_mcq",
        "page_break_before": false,
        "keep_with_next": true,
        "column_span": 1,
        "callout_style": null,
        "heading_level": null
      },
      "publishing_metadata": {
        "target_documents": ["question_bank", "exam_paper", "flashcard_deck"],
        "flashcard_deck": "Physics Unit 2 — Rotational Motion",
        "flashcard_front": "What is the SI unit of angular acceleration?",
        "flashcard_back": "rad/s² (radians per second squared).",
        "glossary_term": "Angular acceleration",
        "glossary_definition": "Rate of change of angular velocity; unit rad/s².",
        "revision_note": "\\( \\alpha \\) unit: rad/s².",
        "teacher_note": "Contrast with linear acceleration (m/s²).",
        "bloom_level": "Remember",
        "learning_objective_tag": "Describe the motion of a rigid object around a fixed axis",
        "concept_map_nodes": [
          {"source": "Angular acceleration", "relation": "unit", "target": "rad/s²"}
        ],
        "workbook_section": "2.2 Rotational Motion",
        "solution_manual_note": "Answer B. α = Δω/Δt, with Δω in rad/s, Δt in s → rad/s²."
      }
    },
    {
      "question_id": "G12_Phy_U2_Q013",
      "generation_timestamp": "2026-06-13T10:35:00Z",
      "grade": "Grade 12",
      "subject": "Physics",
      "unit": "Unit 2: Two-dimensional motion",
      "section": "2.2 Rotational Motion",
      "subsection": "Equation of motion for constant angular acceleration",
      "sub_subsection": null,
      "structural_anchor": "Equation of motion for constant angular acceleration",
      "mcq_type": "C",
      "question": "Which equation correctly gives the final angular velocity \\( \\omega_f \\) for constant angular acceleration \\( \\alpha \\) over time \\( t \\)?",
      "options": {
        "A": "\\( \\omega_f = \\omega_0 + \\alpha t \\)",
        "B": "\\( \\omega_f = \\omega_0 + \\frac{1}{2} \\alpha t^2 \\)",
        "C": "\\( \\omega_f = \\omega_0 t + \\alpha t \\)",
        "D": "\\( \\omega_f = \\omega_0 + \\alpha t^2 \\)"
      },
      "correct_answer": "A",
      "hint": "This is the rotational analog of \\( v_f = v_0 + at \\).",
      "explanation": "For constant angular acceleration, the change in angular velocity is \\( \\alpha t \\), so \\( \\omega_f = \\omega_0 + \\alpha t \\). Option B is the equation for angular displacement, not final angular velocity.",
      "difficulty_level": "easy",
      "formula_used": ["\\(\\omega_f = \\omega_0 + \\alpha t\\)"],
      "numeric": {
        "is_numeric": false,
        "given_values": null,
        "answer_value": null,
        "answer_unit": null,
        "calculation_steps": null,
        "significant_figures": null
      },
      "coverage": {
        "baseline": true,
        "importance_biased": false,
        "structural_element_type": "mini_heading"
      },
      "validation": {
        "no_repetition_confirmed": true,
        "length_constraints_passed": true,
        "symbol_constraints_passed": true,
        "textbook_reference_clean": true,
        "option_parallelism_score": 98,
        "explanation_validation": {
          "word_overlap_percentage": 5.0,
          "named_concept_present": true,
          "distractor_error_identified": true,
          "educational_value_score": 94
        }
      },
      "source_trace": {
        "pdf_unit": "Unit 2: Two-dimensional motion",
        "section_anchor": "2.2 Rotational Motion",
        "subsection_anchor": "Equation of motion for constant angular acceleration",
        "structural_element": "Equation of motion for constant angular acceleration",
        "content_anchor": "ωf = ωo + αΔt",
        "page_hint": 19,
        "concept_hash": "f7a9b1c3d5e7f9a1b3c5d7e9f1a3b5c7d9e1f3a5b7c9d1e3f5a7b9c1d3e5f7"
      },
      "quality_metrics": {
        "stem_complexity_score": 60,
        "distractor_quality_score": 93,
        "cognitive_level": "understand",
        "exam_alignment_score": 93
      },
      "explanations_tiered": {
        "definition": "The equation \\( \\omega_f = \\omega_0 + \\alpha t \\) gives the final angular velocity after time t under constant angular acceleration.",
        "concept_summary": "This rotational kinematics equation is analogous to linear motion's \\( v_f = v_0 + at \\), where \\( \\alpha \\) replaces \\( a \\).",
        "beginner": "If a wheel speeds up steadily, its final spin rate is the starting rate plus how much it increased each second times the number of seconds.",
        "intermediate": "From \\( \\alpha = (\\omega_f - \\omega_0)/t \\), rearranging gives \\( \\omega_f = \\omega_0 + \\alpha t \\).",
        "advanced": "Integrating \\( \\alpha = d\\omega/dt \\) with constant \\( \\alpha \\): \\( \\int_{\\omega_0}^{\\omega_f} d\\omega = \\int_0^t \\alpha dt \\Rightarrow \\omega_f - \\omega_0 = \\alpha t \\).",
        "worked_solution": [],
        "reasoning_steps": [
          "Start with definition of constant angular acceleration: \\( \\alpha = (\\omega_f - \\omega_0)/t \\).",
          "Multiply both sides by t: \\( \\alpha t = \\omega_f - \\omega_0 \\).",
          "Add \\( \\omega_0 \\) to both sides: \\( \\omega_f = \\omega_0 + \\alpha t \\)."
        ],
        "formula_analysis": [
          {
            "formula": "\\(\\omega_f = \\omega_0 + \\alpha t\\)",
            "name": "Angular velocity as a function of time (constant α)",
            "variables": [
              {"symbol": "\\(\\omega_f\\)", "meaning": "Final angular velocity", "unit": "rad/s"},
              {"symbol": "\\(\\omega_0\\)", "meaning": "Initial angular velocity", "unit": "rad/s"},
              {"symbol": "\\(\\alpha\\)", "meaning": "Angular acceleration", "unit": "rad/s²"},
              {"symbol": "\\(t\\)", "meaning": "Time", "unit": "s"}
            ],
            "derivation": "From \\( \\alpha = \\Delta \\omega / \\Delta t \\) with constant α."
          }
        ],
        "misconceptions": [
          "Adding the \\( \\frac{1}{2}\\alpha t^2 \\) term (for displacement) to velocity equation.",
          "Forgetting that \\( \\alpha t \\) is the total change in angular velocity."
        ],
        "related_concepts": ["Rotational kinematics", "Linear vs rotational equations"],
        "revision_note": "\\( \\omega_f = \\omega_0 + \\alpha t \\) (constant α).",
        "glossary_entry": {
          "term": "Angular velocity equation",
          "definition": "For constant angular acceleration, final angular velocity = initial + α × time.",
          "example_equation": "\\(\\omega_f = \\omega_0 + \\alpha t\\)",
          "related_terms": ["Angular acceleration", "Rotational kinematics"]
        },
        "flashcard": {
          "front": "What is the formula for final angular velocity under constant angular acceleration?",
          "back": "\\( \\omega_f = \\omega_0 + \\alpha t \\), analogous to \\( v_f = v_0 + at \\)."
        },
        "concept_map_nodes": [
          {"source": "Constant α", "relation": "gives", "target": "\\(\\omega_f = \\omega_0 + \\alpha t\\)"},
          {"source": "\\(\\omega_f = \\omega_0 + \\alpha t\\)", "relation": "analogous_to", "target": "\\(v_f = v_0 + at\\)"}
        ]
      },
      "visual_system": {
        "requires_visual": false,
        "visual_type": null,
        "visual_title": null,
        "visual_description": null,
        "rendering_target": null,
        "rendering_engine": null,
        "render_width_mm": null,
        "render_height_mm": null,
        "caption": null,
        "accessibility_alt_text": null,
        "geometry_spec": null,
        "graph_spec": null,
        "table_spec": null,
        "circuit_spec": null,
        "chemistry_spec": null,
        "biology_spec": null,
        "flowchart_spec": null,
        "number_line_spec": null
      },
      "layout_metadata": {
        "page_element_type": "mcq_block",
        "suggested_placement": "main_column",
        "visual_anchor": "none",
        "box_type": "standard_mcq",
        "preceding_element": "next_mcq",
        "following_element": "next_mcq",
        "page_break_before": false,
        "keep_with_next": true,
        "column_span": 1,
        "callout_style": null,
        "heading_level": null
      },
      "publishing_metadata": {
        "target_documents": ["question_bank", "exam_paper", "flashcard_deck"],
        "flashcard_deck": "Physics Unit 2 — Rotational Motion",
        "flashcard_front": "Write the equation for final angular velocity under constant angular acceleration.",
        "flashcard_back": "\\( \\omega_f = \\omega_0 + \\alpha t \\).",
        "glossary_term": "Angular velocity equation",
        "glossary_definition": "ωf = ω0 + αt for constant α.",
        "revision_note": "ωf = ω0 + αt.",
        "teacher_note": "Point out analogy with linear motion to aid memory.",
        "bloom_level": "Understand",
        "learning_objective_tag": "Derive equations of motion with constant angular acceleration",
        "concept_map_nodes": [
          {"source": "Rotational kinematics", "relation": "includes", "target": "\\(\\omega_f = \\omega_0 + \\alpha t\\)"}
        ],
        "workbook_section": "2.2 Rotational Motion",
        "solution_manual_note": "Answer A. Rotational analog of vf = v0 + at."
      }
    },
    {
      "question_id": "G12_Phy_U2_Q014",
      "generation_timestamp": "2026-06-13T10:35:00Z",
      "grade": "Grade 12",
      "subject": "Physics",
      "unit": "Unit 2: Two-dimensional motion",
      "section": "2.2 Rotational Motion",
      "subsection": "Equation of motion for constant angular acceleration",
      "sub_subsection": null,
      "structural_anchor": "Equation of motion for constant angular acceleration",
      "mcq_type": "C",
      "question": "For constant angular acceleration \\( \\alpha \\), which equation gives the angular displacement \\( \\Delta \\theta \\) after time \\( t \\)?",
      "options": {
        "A": "\\( \\Delta \\theta = \\omega_0 t + \\alpha t \\)",
        "B": "\\( \\Delta \\theta = \\omega_0 t + \\frac{1}{2} \\alpha t^2 \\)",
        "C": "\\( \\Delta \\theta = \\frac{1}{2} \\alpha t^2 \\)",
        "D": "\\( \\Delta \\theta = \\omega_0 t \\)"
      },
      "correct_answer": "B",
      "hint": "This is the rotational analog of \\( \\Delta x = v_0 t + \\frac{1}{2} a t^2 \\).",
      "explanation": "The correct kinematic equation for angular displacement under constant \\( \\alpha \\) is \\( \\Delta \\theta = \\omega_0 t + \\frac{1}{2} \\alpha t^2 \\). Option C applies only if \\( \\omega_0 = 0 \\) (starting from rest).",
      "difficulty_level": "medium",
      "formula_used": ["\\(\\Delta \\theta = \\omega_0 t + \\frac{1}{2} \\alpha t^2\\)"],
      "numeric": {
        "is_numeric": false,
        "given_values": null,
        "answer_value": null,
        "answer_unit": null,
        "calculation_steps": null,
        "significant_figures": null
      },
      "coverage": {
        "baseline": true,
        "importance_biased": false,
        "structural_element_type": "mini_heading"
      },
      "validation": {
        "no_repetition_confirmed": true,
        "length_constraints_passed": true,
        "symbol_constraints_passed": true,
        "textbook_reference_clean": true,
        "option_parallelism_score": 97,
        "explanation_validation": {
          "word_overlap_percentage": 4.0,
          "named_concept_present": true,
          "distractor_error_identified": true,
          "educational_value_score": 93
        }
      },
      "source_trace": {
        "pdf_unit": "Unit 2: Two-dimensional motion",
        "section_anchor": "2.2 Rotational Motion",
        "subsection_anchor": "Equation of motion for constant angular acceleration",
        "structural_element": "Equation of motion for constant angular acceleration",
        "content_anchor": "Δθ = ω₀Δt + ½αΔt²",
        "page_hint": 19,
        "concept_hash": "a8b0c2d4e6f8a0b2c4d6e8f0a2b4c6d8e0f2a4b6c8d0e2f4a6b8c0d2e4f6a8"
      },
      "quality_metrics": {
        "stem_complexity_score": 65,
        "distractor_quality_score": 90,
        "cognitive_level": "understand",
        "exam_alignment_score": 92
      },
      "explanations_tiered": {
        "definition": "Angular displacement under constant angular acceleration is given by \\( \\Delta \\theta = \\omega_0 t + \\frac{1}{2} \\alpha t^2 \\).",
        "concept_summary": "This equation accounts for displacement due to initial angular velocity plus additional displacement from angular acceleration.",
        "beginner": "If a wheel starts spinning and also speeds up, its total angle turned is from the starting speed plus extra from getting faster.",
        "intermediate": "Derived from \\( \\omega_{\\text{avg}} = (\\omega_0 + \\omega_f)/2 \\) and \\( \\omega_f = \\omega_0 + \\alpha t \\), then \\( \\Delta \\theta = \\omega_{\\text{avg}} t \\).",
        "advanced": "Integrate \\( \\omega(t) = \\omega_0 + \\alpha t \\) to get \\( \\theta(t) - \\theta_0 = \\omega_0 t + \\frac{1}{2} \\alpha t^2 \\).",
        "worked_solution": [],
        "reasoning_steps": [
          "Start with average angular velocity: \\( \\omega_{\\text{avg}} = (\\omega_0 + \\omega_f)/2 \\).",
          "Substitute \\( \\omega_f = \\omega_0 + \\alpha t \\): \\( \\omega_{\\text{avg}} = \\omega_0 + \\frac{1}{2} \\alpha t \\).",
          "Then \\( \\Delta \\theta = \\omega_{\\text{avg}} t = \\omega_0 t + \\frac{1}{2} \\alpha t^2 \\)."
        ],
        "formula_analysis": [
          {
            "formula": "\\(\\Delta \\theta = \\omega_0 t + \\frac{1}{2} \\alpha t^2\\)",
            "name": "Angular displacement (constant α)",
            "variables": [
              {"symbol": "\\(\\Delta \\theta\\)", "meaning": "Angular displacement", "unit": "rad"},
              {"symbol": "\\(\\omega_0\\)", "meaning": "Initial angular velocity", "unit": "rad/s"},
              {"symbol": "\\(\\alpha\\)", "meaning": "Angular acceleration", "unit": "rad/s²"},
              {"symbol": "\\(t\\)", "meaning": "Time", "unit": "s"}
            ],
            "derivation": "Integration of \\( \\omega(t) = \\omega_0 + \\alpha t \\)."
          }
        ],
        "misconceptions": [
          "Using \\( \\frac{1}{2} \\alpha t^2 \\) alone and omitting \\( \\omega_0 t \\) when starting from non-zero initial speed.",
          "Confusing angular displacement equation with angular velocity equation."
        ],
        "related_concepts": ["Rotational kinematics", "Constant acceleration motion"],
        "revision_note": "Δθ = ω₀t + ½αt² (constant α).",
        "glossary_entry": {
          "term": "Angular displacement equation",
          "definition": "Δθ = ω₀t + ½αt² for constant angular acceleration.",
          "example_equation": "\\(\\Delta \\theta = \\omega_0 t + \\frac{1}{2} \\alpha t^2\\)",
          "related_terms": ["Angular displacement", "Angular acceleration"]
        },
        "flashcard": {
          "front": "What is the formula for angular displacement under constant angular acceleration?",
          "back": "\\( \\Delta \\theta = \\omega_0 t + \\frac{1}{2} \\alpha t^2 \\)."
        },
        "concept_map_nodes": [
          {"source": "Constant α", "relation": "gives", "target": "\\(\\Delta \\theta = \\omega_0 t + \\frac{1}{2} \\alpha t^2\\)"},
          {"source": "\\(\\Delta \\theta = \\omega_0 t + \\frac{1}{2} \\alpha t^2\\)", "relation": "analogous_to", "target": "\\(\\Delta x = v_0 t + \\frac{1}{2} a t^2\\)"}
        ]
      },
      "visual_system": {
        "requires_visual": false,
        "visual_type": null,
        "visual_title": null,
        "visual_description": null,
        "rendering_target": null,
        "rendering_engine": null,
        "render_width_mm": null,
        "render_height_mm": null,
        "caption": null,
        "accessibility_alt_text": null,
        "geometry_spec": null,
        "graph_spec": null,
        "table_spec": null,
        "circuit_spec": null,
        "chemistry_spec": null,
        "biology_spec": null,
        "flowchart_spec": null,
        "number_line_spec": null
      },
      "layout_metadata": {
        "page_element_type": "mcq_block",
        "suggested_placement": "main_column",
        "visual_anchor": "none",
        "box_type": "standard_mcq",
        "preceding_element": "next_mcq",
        "following_element": "next_mcq",
        "page_break_before": false,
        "keep_with_next": true,
        "column_span": 1,
        "callout_style": null,
        "heading_level": null
      },
      "publishing_metadata": {
        "target_documents": ["question_bank", "exam_paper", "flashcard_deck"],
        "flashcard_deck": "Physics Unit 2 — Rotational Motion",
        "flashcard_front": "Give the angular displacement formula for constant angular acceleration.",
        "flashcard_back": "Δθ = ω₀t + ½αt².",
        "glossary_term": "Angular displacement equation",
        "glossary_definition": "Δθ = ω₀t + ½αt² for constant α.",
        "revision_note": "Δθ = ω₀t + ½αt².",
        "teacher_note": "Reinforce that both terms (initial velocity and acceleration) contribute to displacement.",
        "bloom_level": "Understand",
        "learning_objective_tag": "Derive equations of motion with constant angular acceleration",
        "concept_map_nodes": [
          {"source": "Rotational kinematics", "relation": "includes", "target": "\\(\\Delta \\theta = \\omega_0 t + \\frac{1}{2} \\alpha t^2\\)"}
        ],
        "workbook_section": "2.2 Rotational Motion",
        "solution_manual_note": "Answer B. Rotational analog of Δx = v₀t + ½at²."
      }
    },
    {
      "question_id": "G12_Phy_U2_Q015",
      "generation_timestamp": "2026-06-13T10:35:00Z",
      "grade": "Grade 12",
      "subject": "Physics",
      "unit": "Unit 2: Two-dimensional motion",
      "section": "2.2 Rotational Motion",
      "subsection": "Relationship between angular motion and translational motion quantities",
      "sub_subsection": null,
      "structural_anchor": "Relationship between angular motion and translational motion quantities",
      "mcq_type": "C",
      "question": "A wheel of radius \\( r = 0.5 \\, \\text{m} \\) rotates with angular speed \\( \\omega = 10 \\, \\text{rad/s} \\). What is the linear (tangential) speed \\( v \\) of a point on the rim?",
      "options": {
        "A": "\\( 0.5 \\, \\text{m/s} \\)",
        "B": "\\( 5.0 \\, \\text{m/s} \\)",
        "C": "\\( 10.0 \\, \\text{m/s} \\)",
        "D": "\\( 20.0 \\, \\text{m/s} \\)"
      },
      "correct_answer": "B",
      "hint": "Use \\( v = r \\omega \\).",
      "explanation": "Tangential speed \\( v = r \\omega = 0.5 \\times 10 = 5.0 \\, \\text{m/s} \\). Option A incorrectly divides \\( r / \\omega \\), while option D multiplies incorrectly.",
      "difficulty_level": "medium",
      "formula_used": ["\\(v = r \\omega\\)"],
      "numeric": {
        "is_numeric": true,
        "given_values": {
          "\\(r\\)": {"magnitude": 0.5, "unit": "m"},
          "\\(\\omega\\)": {"magnitude": 10, "unit": "rad/s"}
        },
        "answer_value": 5.0,
        "answer_unit": "m/s",
        "calculation_steps": [
          "Tangential speed formula: \\( v = r \\omega \\)",
          "Substitute: \\( v = 0.5 \\times 10 \\)",
          "\\( v = 5.0 \\, \\text{m/s} \\)"
        ],
        "significant_figures": 2
      },
      "coverage": {
        "baseline": true,
        "importance_biased": false,
        "structural_element_type": "mini_heading"
      },
      "validation": {
        "no_repetition_confirmed": true,
        "length_constraints_passed": true,
        "symbol_constraints_passed": true,
        "textbook_reference_clean": true,
        "option_parallelism_score": 96,
        "explanation_validation": {
          "word_overlap_percentage": 4.0,
          "named_concept_present": true,
          "distractor_error_identified": true,
          "educational_value_score": 94
        }
      },
      "source_trace": {
        "pdf_unit": "Unit 2: Two-dimensional motion",
        "section_anchor": "2.2 Rotational Motion",
        "subsection_anchor": "Relationship between angular motion and translational motion quantities",
        "structural_element": "Relationship between angular motion and translational motion quantities",
        "content_anchor": "v = ωr",
        "page_hint": 24,
        "concept_hash": "b9c1d3e5f7a9b1c3d5e7f9a1b3c5d7e9f1a3b5c7d9e1f3a5b7c9d1e3f5a7b9"
      },
      "quality_metrics": {
        "stem_complexity_score": 65,
        "distractor_quality_score": 88,
        "cognitive_level": "apply",
        "exam_alignment_score": 94
      },
      "explanations_tiered": {
        "definition": "Tangential speed is the linear speed of a point on a rotating object, given by \\( v = r \\omega \\).",
        "concept_summary": "All points on a rigid rotating body have the same angular speed \\( \\omega \\), but tangential speed increases with radius according to \\( v = r \\omega \\).",
        "beginner": "A point farther from the center moves faster in meters per second than a point near the center, even though both turn at the same rate.",
        "intermediate": "From arc length \\( s = r \\theta \\), divide by time: \\( v = r \\omega \\). This relates linear and angular speeds.",
        "advanced": "Differentiating \\( s = r \\theta \\) (with constant \\( r \\)) gives \\( ds/dt = r \\, d\\theta/dt \\), hence \\( v = r \\omega \\).",
        "worked_solution": [
          "Step 1: Recall the relationship \\( v = r \\omega \\).",
          "Step 2: Substitute \\( r = 0.5 \\, \\text{m} \\), \\( \\omega = 10 \\, \\text{rad/s} \\).",
          "Step 3: Calculate \\( v = 0.5 \\times 10 = 5.0 \\, \\text{m/s} \\)."
        ],
        "reasoning_steps": [
          "Identify the formula connecting linear and angular speed: \\( v = r \\omega \\).",
          "Plug in the given radius and angular speed.",
          "Compute the product to find tangential speed."
        ],
        "formula_analysis": [
          {
            "formula": "\\(v = r \\omega\\)",
            "name": "Tangential speed",
            "variables": [
              {"symbol": "\\(v\\)", "meaning": "Tangential (linear) speed", "unit": "m/s"},
              {"symbol": "\\(r\\)", "meaning": "Radius from axis of rotation", "unit": "m"},
              {"symbol": "\\(\\omega\\)", "meaning": "Angular speed", "unit": "rad/s"}
            ],
            "derivation": "From \\( s = r\\theta \\), differentiate: \\( v = r \\omega \\)."
          }
        ],
        "misconceptions": [
          "Using \\( v = \\omega / r \\) (inverting the relationship).",
          "Thinking all points on a wheel have the same linear speed (false; only same angular speed)."
        ],
        "related_concepts": ["Angular speed", "Tangential acceleration", "Arc length"],
        "revision_note": "\\( v = r \\omega \\).",
        "glossary_entry": {
          "term": "Tangential speed",
          "definition": "Linear speed of a point on a rotating object; equals radius times angular speed.",
          "example_equation": "\\(v = r \\omega\\)",
          "related_terms": ["Angular speed", "Radius"]
        },
        "flashcard": {
          "front": "How do you calculate tangential speed from angular speed and radius?",
          "back": "\\( v = r \\omega \\). Derived from \\( s = r\\theta \\) divided by time."
        },
        "concept_map_nodes": [
          {"source": "Tangential speed", "relation": "equals", "target": "\\(r \\omega\\)"},
          {"source": "Tangential speed", "relation": "depends_on", "target": "Radius"}
        ]
      },
      "visual_system": {
        "requires_visual": false,
        "visual_type": null,
        "visual_title": null,
        "visual_description": null,
        "rendering_target": null,
        "rendering_engine": null,
        "render_width_mm": null,
        "render_height_mm": null,
        "caption": null,
        "accessibility_alt_text": null,
        "geometry_spec": null,
        "graph_spec": null,
        "table_spec": null,
        "circuit_spec": null,
        "chemistry_spec": null,
        "biology_spec": null,
        "flowchart_spec": null,
        "number_line_spec": null
      },
      "layout_metadata": {
        "page_element_type": "mcq_block",
        "suggested_placement": "main_column",
        "visual_anchor": "none",
        "box_type": "standard_mcq",
        "preceding_element": "next_mcq",
        "following_element": "next_mcq",
        "page_break_before": false,
        "keep_with_next": true,
        "column_span": 1,
        "callout_style": null,
        "heading_level": null
      },
      "publishing_metadata": {
        "target_documents": ["question_bank", "exam_paper", "workbook", "solution_manual"],
        "flashcard_deck": "Physics Unit 2 — Rotational Motion",
        "flashcard_front": "A 0.5 m radius wheel spins at 10 rad/s. Find rim speed.",
        "flashcard_back": "\\( v = r\\omega = 0.5 \\times 10 = 5.0 \\, \\text{m/s} \\).",
        "glossary_term": "Tangential speed",
        "glossary_definition": "Linear speed of a point on a rotating object, v = rω.",
        "revision_note": "v = rω.",
        "teacher_note": "Reinforce that all points share ω, but v varies with r.",
        "bloom_level": "Apply",
        "learning_objective_tag": "Apply equations to solve problems related to rotational motion",
        "concept_map_nodes": [
          {"source": "Tangential speed", "relation": "formula", "target": "v = rω"}
        ],
        "workbook_section": "2.2 Rotational Motion",
        "solution_manual_note": "Answer B. v = rω = 0.5 × 10 = 5.0 m/s."
      }
    },
    {
      "question_id": "G12_Phy_U2_Q016",
      "generation_timestamp": "2026-06-13T10:35:00Z",
      "grade": "Grade 12",
      "subject": "Physics",
      "unit": "Unit 2: Two-dimensional motion",
      "section": "2.2 Rotational Motion",
      "subsection": "Relationship between angular motion and translational motion quantities",
      "sub_subsection": null,
      "structural_anchor": "Relationship between angular motion and translational motion quantities",
      "mcq_type": "C",
      "question": "A wheel has angular acceleration \\( \\alpha = 2.0 \\, \\text{rad/s}^2 \\) and radius \\( r = 0.8 \\, \\text{m} \\). What is the tangential acceleration \\( a_t \\) of a point on the rim?",
      "options": {
        "A": "\\( 0.4 \\, \\text{m/s}^2 \\)",
        "B": "\\( 1.6 \\, \\text{m/s}^2 \\)",
        "C": "\\( 2.0 \\, \\text{m/s}^2 \\)",
        "D": "\\( 2.5 \\, \\text{m/s}^2 \\)"
      },
      "correct_answer": "B",
      "hint": "Use \\( a_t = r \\alpha \\).",
      "explanation": "Tangential acceleration \\( a_t = r \\alpha = 0.8 \\times 2.0 = 1.6 \\, \\text{m/s}^2 \\). Option A incorrectly divides \\( r / \\alpha \\), and option C uses \\( \\alpha \\) alone without multiplying by radius.",
      "difficulty_level": "medium",
      "formula_used": ["\\(a_t = r \\alpha\\)"],
      "numeric": {
        "is_numeric": true,
        "given_values": {
          "\\(r\\)": {"magnitude": 0.8, "unit": "m"},
          "\\(\\alpha\\)": {"magnitude": 2.0, "unit": "rad/s²"}
        },
        "answer_value": 1.6,
        "answer_unit": "m/s²",
        "calculation_steps": [
          "Tangential acceleration formula: \\( a_t = r \\alpha \\)",
          "Substitute: \\( a_t = 0.8 \\times 2.0 \\)",
          "\\( a_t = 1.6 \\, \\text{m/s}^2 \\)"
        ],
        "significant_figures": 2
      },
      "coverage": {
        "baseline": true,
        "importance_biased": false,
        "structural_element_type": "mini_heading"
      },
      "validation": {
        "no_repetition_confirmed": true,
        "length_constraints_passed": true,
        "symbol_constraints_passed": true,
        "textbook_reference_clean": true,
        "option_parallelism_score": 96,
        "explanation_validation": {
          "word_overlap_percentage": 3.0,
          "named_concept_present": true,
          "distractor_error_identified": true,
          "educational_value_score": 94
        }
      },
      "source_trace": {
        "pdf_unit": "Unit 2: Two-dimensional motion",
        "section_anchor": "2.2 Rotational Motion",
        "subsection_anchor": "Relationship between angular motion and translational motion quantities",
        "structural_element": "Relationship between angular motion and translational motion quantities",
        "content_anchor": "a = rα",
        "page_hint": 24,
        "concept_hash": "c0d2e4f6a8b0c2d4e6f8a0b2c4d6e8f0a2b4c6d8e0f2a4b6c8d0e2f4a6b8c0"
      },
      "quality_metrics": {
        "stem_complexity_score": 65,
        "distractor_quality_score": 89,
        "cognitive_level": "apply",
        "exam_alignment_score": 94
      },
      "explanations_tiered": {
        "definition": "Tangential acceleration is the linear acceleration of a point on a rotating object, given by \\( a_t = r \\alpha \\).",
        "concept_summary": "For a rigid body, tangential acceleration at a point is radius times angular acceleration, analogous to \\( a = r \\alpha \\).",
        "beginner": "If a wheel spins faster and faster, a point on the edge speeds up more quickly in meters per second each second than a point near the center.",
        "intermediate": "From \\( v = r \\omega \\), differentiate with respect to time (r constant): \\( dv/dt = r \\, d\\omega/dt \\), so \\( a_t = r \\alpha \\).",
        "advanced": "Taking time derivative of \\( \\vec{v} = \\vec{\\omega} \\times \\vec{r} \\) gives tangential component \\( a_t = r \\alpha \\) when \\( \\alpha \\) is perpendicular to \\( r \\).",
        "worked_solution": [
          "Step 1: Recall \\( a_t = r \\alpha \\).",
          "Step 2: Substitute \\( r = 0.8 \\, \\text{m} \\), \\( \\alpha = 2.0 \\, \\text{rad/s}^2 \\).",
          "Step 3: Calculate \\( a_t = 0.8 \\times 2.0 = 1.6 \\, \\text{m/s}^2 \\)."
        ],
        "reasoning_steps": [
          "Identify formula: \\( a_t = r \\alpha \\).",
          "Plug in radius and angular acceleration.",
          "Compute product."
        ],
        "formula_analysis": [
          {
            "formula": "\\(a_t = r \\alpha\\)",
            "name": "Tangential acceleration",
            "variables": [
              {"symbol": "\\(a_t\\)", "meaning": "Tangential acceleration", "unit": "m/s²"},
              {"symbol": "\\(r\\)", "meaning": "Radius", "unit": "m"},
              {"symbol": "\\(\\alpha\\)", "meaning": "Angular acceleration", "unit": "rad/s²"}
            ],
            "derivation": "Differentiate \\( v = r\\omega \\) with respect to time."
          }
        ],
        "misconceptions": [
          "Using \\( a_t = \\alpha / r \\) (inverting).",
          "Confusing tangential acceleration with centripetal acceleration (\\( a_c = v^2/r \\) or \\( r\\omega^2 \\))."
        ],
        "related_concepts": ["Angular acceleration", "Tangential speed", "Centripetal acceleration"],
        "revision_note": "\\( a_t = r \\alpha \\).",
        "glossary_entry": {
          "term": "Tangential acceleration",
          "definition": "Linear acceleration of a point on a rotating object tangent to its circular path.",
          "example_equation": "\\(a_t = r \\alpha\\)",
          "related_terms": ["Angular acceleration", "Centripetal acceleration"]
        },
        "flashcard": {
          "front": "How do you find tangential acceleration from angular acceleration?",
          "back": "\\( a_t = r \\alpha \\), where r is the radius from the axis of rotation."
        },
        "concept_map_nodes": [
          {"source": "Tangential acceleration", "relation": "equals", "target": "\\(r \\alpha\\)"},
          {"source": "Tangential acceleration", "relation": "caused_by", "target": "Angular acceleration"}
        ]
      },
      "visual_system": {
        "requires_visual": false,
        "visual_type": null,
        "visual_title": null,
        "visual_description": null,
        "rendering_target": null,
        "rendering_engine": null,
        "render_width_mm": null,
        "render_height_mm": null,
        "caption": null,
        "accessibility_alt_text": null,
        "geometry_spec": null,
        "graph_spec": null,
        "table_spec": null,
        "circuit_spec": null,
        "chemistry_spec": null,
        "biology_spec": null,
        "flowchart_spec": null,
        "number_line_spec": null
      },
      "layout_metadata": {
        "page_element_type": "mcq_block",
        "suggested_placement": "main_column",
        "visual_anchor": "none",
        "box_type": "standard_mcq",
        "preceding_element": "next_mcq",
        "following_element": "next_mcq",
        "page_break_before": false,
        "keep_with_next": true,
        "column_span": 1,
        "callout_style": null,
        "heading_level": null
      },
      "publishing_metadata": {
        "target_documents": ["question_bank", "exam_paper", "workbook", "solution_manual"],
        "flashcard_deck": "Physics Unit 2 — Rotational Motion",
        "flashcard_front": "A wheel (r=0.8 m) has α=2.0 rad/s². Find tangential acceleration.",
        "flashcard_back": "\\( a_t = r\\alpha = 0.8 \\times 2.0 = 1.6 \\, \\text{m/s}^2 \\).",
        "glossary_term": "Tangential acceleration",
        "glossary_definition": "at = rα.",
        "revision_note": "at = rα.",
        "teacher_note": "Distinguish tangential (changes speed) from centripetal (changes direction).",
        "bloom_level": "Apply",
        "learning_objective_tag": "Apply equations to solve problems related to rotational motion",
        "concept_map_nodes": [
          {"source": "Tangential acceleration", "relation": "formula", "target": "a_t = rα"}
        ],
        "workbook_section": "2.2 Rotational Motion",
        "solution_manual_note": "Answer B. a_t = rα = 0.8 × 2.0 = 1.6 m/s²."
      }
    },
    {
      "question_id": "G12_Phy_U2_Q017",
      "generation_timestamp": "2026-06-13T10:35:00Z",
      "grade": "Grade 12",
      "subject": "Physics",
      "unit": "Unit 2: Two-dimensional motion",
      "section": "2.3 Rotational Dynamics",
      "subsection": "Torque",
      "sub_subsection": null,
      "structural_anchor": "Torque",
      "mcq_type": "A",
      "question": "Torque is defined as the rotational effect of a force. Which equation correctly gives the magnitude of torque?",
      "options": {
        "A": "\\( \\tau = rF \\sin \\theta \\)",
        "B": "\\( \\tau = rF \\cos \\theta \\)",
        "C": "\\( \\tau = F / r \\sin \\theta \\)",
        "D": "\\( \\tau = r / F \\sin \\theta \\)"
      },
      "correct_answer": "A",
      "hint": "Only the perpendicular component of force produces torque.",
      "explanation": "Torque magnitude \\( \\tau = rF \\sin \\theta \\), where \\( \\theta \\) is the angle between \\( \\vec{r} \\) (lever arm) and \\( \\vec{F} \\). Option B uses cosine, which gives the component parallel to \\( r \\), not perpendicular.",
      "difficulty_level": "easy",
      "formula_used": ["\\(\\tau = rF \\sin \\theta\\)"],
      "numeric": {
        "is_numeric": false,
        "given_values": null,
        "answer_value": null,
        "answer_unit": null,
        "calculation_steps": null,
        "significant_figures": null
      },
      "coverage": {
        "baseline": true,
        "importance_biased": false,
        "structural_element_type": "mini_heading"
      },
      "validation": {
        "no_repetition_confirmed": true,
        "length_constraints_passed": true,
        "symbol_constraints_passed": true,
        "textbook_reference_clean": true,
        "option_parallelism_score": 98,
        "explanation_validation": {
          "word_overlap_percentage": 0.0,
          "named_concept_present": true,
          "distractor_error_identified": true,
          "educational_value_score": 93
        }
      },
      "source_trace": {
        "pdf_unit": "Unit 2: Two-dimensional motion",
        "section_anchor": "2.3 Rotational Dynamics",
        "subsection_anchor": "Torque",
        "structural_element": "Torque",
        "content_anchor": "τ = rF sin θ",
        "page_hint": 27,
        "concept_hash": "d1e3f5a7b9c1d3e5f7a9b1c3d5e7f9a1b3c5d7e9f1a3b5c7d9e1f3a5b7c9d1"
      },
      "quality_metrics": {
        "stem_complexity_score": 58,
        "distractor_quality_score": 94,
        "cognitive_level": "remembering",
        "exam_alignment_score": 92
      },
      "explanations_tiered": {
        "definition": "Torque is the rotational equivalent of force, causing angular acceleration.",
        "concept_summary": "Torque magnitude = lever arm distance × force × sine of the angle between them; only the perpendicular force component contributes.",
        "beginner": "Pushing a door near the hinge (small r) or at an angle makes it harder to open; torque depends on both how hard and where you push.",
        "intermediate": "Only the component of force perpendicular to the radius vector produces rotation: \\( \\tau = r (F \\sin \\theta) = rF \\sin \\theta \\).",
        "advanced": "Vectorially, \\( \\vec{\\tau} = \\vec{r} \\times \\vec{F} \\); magnitude \\( |\\vec{\\tau}| = rF \\sin \\theta \\).",
        "worked_solution": [],
        "reasoning_steps": [
          "Identify lever arm length r.",
          "Identify force magnitude F.",
          "Find angle θ between r and F.",
          "Compute τ = rF sin θ."
        ],
        "formula_analysis": [
          {
            "formula": "\\(\\tau = rF \\sin \\theta\\)",
            "name": "Torque magnitude",
            "variables": [
              {"symbol": "\\(\\tau\\)", "meaning": "Torque", "unit": "N·m"},
              {"symbol": "\\(r\\)", "meaning": "Lever arm distance from pivot", "unit": "m"},
              {"symbol": "\\(F\\)", "meaning": "Force magnitude", "unit": "N"},
              {"symbol": "\\(\\theta\\)", "meaning": "Angle between r and F", "unit": "degrees or rad"}
            ],
            "derivation": "Definition of cross product."
          }
        ],
        "misconceptions": [
          "Using cosine instead of sine (cosine gives component parallel to r, which does not produce torque).",
          "Forgetting that r is perpendicular distance from pivot to line of action (lever arm)."
        ],
        "related_concepts": ["Lever arm", "Cross product", "Rotational dynamics"],
        "revision_note": "τ = rF sin θ. Perpendicular component matters.",
        "glossary_entry": {
          "term": "Torque",
          "definition": "Rotational effect of a force; magnitude τ = rF sin θ.",
          "example_equation": "\\(\\tau = rF \\sin \\theta\\)",
          "related_terms": ["Lever arm", "Angular acceleration"]
        },
        "flashcard": {
          "front": "What is the formula for torque magnitude?",
          "back": "\\( \\tau = rF \\sin \\theta \\), where θ is the angle between r and F."
        },
        "concept_map_nodes": [
          {"source": "Torque", "relation": "equals", "target": "\\(rF \\sin \\theta\\)"},
          {"source": "Torque", "relation": "causes", "target": "Angular acceleration"}
        ]
      },
      "visual_system": {
        "requires_visual": false,
        "visual_type": null,
        "visual_title": null,
        "visual_description": null,
        "rendering_target": null,
        "rendering_engine": null,
        "render_width_mm": null,
        "render_height_mm": null,
        "caption": null,
        "accessibility_alt_text": null,
        "geometry_spec": null,
        "graph_spec": null,
        "table_spec": null,
        "circuit_spec": null,
        "chemistry_spec": null,
        "biology_spec": null,
        "flowchart_spec": null,
        "number_line_spec": null
      },
      "layout_metadata": {
        "page_element_type": "mcq_block",
        "suggested_placement": "main_column",
        "visual_anchor": "none",
        "box_type": "standard_mcq",
        "preceding_element": "section_heading",
        "following_element": "next_mcq",
        "page_break_before": false,
        "keep_with_next": true,
        "column_span": 1,
        "callout_style": null,
        "heading_level": null
      },
      "publishing_metadata": {
        "target_documents": ["question_bank", "exam_paper", "flashcard_deck"],
        "flashcard_deck": "Physics Unit 2 — Rotational Dynamics",
        "flashcard_front": "How do you calculate torque magnitude?",
        "flashcard_back": "τ = rF sin θ, where θ is the angle between position vector r and force F.",
        "glossary_term": "Torque",
        "glossary_definition": "Rotational effect of force; τ = rF sin θ.",
        "revision_note": "τ = rF sin θ.",
        "teacher_note": "Emphasize that torque is a vector, direction given by right-hand rule.",
        "bloom_level": "Remember",
        "learning_objective_tag": "Define torque in terms of force and distance from axis of rotation",
        "concept_map_nodes": [
          {"source": "Torque", "relation": "formula", "target": "τ = rF sin θ"}
        ],
        "workbook_section": "2.3 Rotational Dynamics",
        "solution_manual_note": "Answer A. Torque = rF sin θ, from τ = r × F."
      }
    },
    {
      "question_id": "G12_Phy_U2_Q018",
      "generation_timestamp": "2026-06-13T10:35:00Z",
      "grade": "Grade 12",
      "subject": "Physics",
      "unit": "Unit 2: Two-dimensional motion",
      "section": "2.3 Rotational Dynamics",
      "subsection": "Torque",
      "sub_subsection": null,
      "structural_anchor": "Torque",
      "mcq_type": "D",
      "question": "A force of \\( F = 20 \\, \\text{N} \\) is applied perpendicularly at the end of a wrench handle of length \\( r = 0.30 \\, \\text{m} \\). What torque is applied?",
      "options": {
        "A": "\\( 0.67 \\, \\text{N·m} \\)",
        "B": "\\( 6.0 \\, \\text{N·m} \\)",
        "C": "\\( 20 \\, \\text{N·m} \\)",
        "D": "\\( 60 \\, \\text{N·m} \\)"
      },
      "correct_answer": "B",
      "hint": "For perpendicular force, τ = rF.",
      "explanation": "With \\( \\theta = 90^\\circ \\), \\( \\sin 90^\\circ = 1 \\), so \\( \\tau = rF = 0.30 \\times 20 = 6.0 \\, \\text{N·m} \\). Option A incorrectly divides r/F, and option D multiplies incorrectly with wrong units.",
      "difficulty_level": "medium",
      "formula_used": ["\\(\\tau = rF\\)"],
      "numeric": {
        "is_numeric": true,
        "given_values": {
          "\\(r\\)": {"magnitude": 0.30, "unit": "m"},
          "\\(F\\)": {"magnitude": 20, "unit": "N"}
        },
        "answer_value": 6.0,
        "answer_unit": "N·m",
        "calculation_steps": [
          "Torque for perpendicular force: τ = rF",
          "τ = 0.30 × 20",
          "τ = 6.0 N·m"
        ],
        "significant_figures": 2
      },
      "coverage": {
        "baseline": true,
        "importance_biased": false,
        "structural_element_type": "mini_heading"
      },
      "validation": {
        "no_repetition_confirmed": true,
        "length_constraints_passed": true,
        "symbol_constraints_passed": true,
        "textbook_reference_clean": true,
        "option_parallelism_score": 96,
        "explanation_validation": {
          "word_overlap_percentage": 4.0,
          "named_concept_present": true,
          "distractor_error_identified": true,
          "educational_value_score": 94
        }
      },
      "source_trace": {
        "pdf_unit": "Unit 2: Two-dimensional motion",
        "section_anchor": "2.3 Rotational Dynamics",
        "subsection_anchor": "Torque",
        "structural_element": "Torque",
        "content_anchor": "τ = rF sin θ",
        "page_hint": 27,
        "concept_hash": "e2f4a6b8c0d2e4f6a8b0c2d4e6f8a0b2c4d6e8f0a2b4c6d8e0f2a4b6c8d0e2"
      },
      "quality_metrics": {
        "stem_complexity_score": 62,
        "distractor_quality_score": 90,
        "cognitive_level": "apply",
        "exam_alignment_score": 93
      },
      "explanations_tiered": {
        "definition": "Torque is the product of lever arm length and perpendicular force component.",
        "concept_summary": "When force is perpendicular to the lever arm, torque simplifies to τ = rF.",
        "beginner": "Pushing at a right angle on a wrench gives the most turning effect for a given force.",
        "intermediate": "Since θ = 90°, sin 90° = 1, τ = rF sin θ = rF.",
        "advanced": "From τ = rF sin θ, when sin θ = 1 (force perpendicular), torque is maximized for given r and F.",
        "worked_solution": [
          "Step 1: Force is perpendicular → θ = 90°, sin θ = 1.",
          "Step 2: Use τ = rF.",
          "Step 3: τ = 0.30 m × 20 N = 6.0 N·m."
        ],
        "reasoning_steps": [
          "Note that force is perpendicular to wrench, so sin 90° = 1.",
          "Apply torque formula τ = rF.",
          "Compute product."
        ],
        "formula_analysis": [
          {
            "formula": "\\(\\tau = rF\\)",
            "name": "Torque (perpendicular force)",
            "variables": [
              {"symbol": "\\(\\tau\\)", "meaning": "Torque", "unit": "N·m"},
              {"symbol": "\\(r\\)", "meaning": "Lever arm length", "unit": "m"},
              {"symbol": "\\(F\\)", "meaning": "Force", "unit": "N"}
            ],
            "derivation": "Special case of τ = rF sin θ with θ = 90°."
          }
        ],
        "misconceptions": [
          "Forgetting to multiply by the lever arm (using just force).",
          "Using τ = F/r instead of rF."
        ],
        "related_concepts": ["Lever arm", "Maximum torque", "Cross product"],
        "revision_note": "Perpendicular force: τ = rF.",
        "glossary_entry": {
          "term": "Torque (perpendicular case)",
          "definition": "When force is perpendicular to lever arm, torque = rF.",
          "example_equation": "\\(\\tau = rF\\)",
          "related_terms": ["Lever arm", "Maximum torque"]
        },
        "flashcard": {
          "front": "A 20 N perpendicular force on a 0.30 m wrench produces what torque?",
          "back": "τ = rF = 0.30 × 20 = 6.0 N·m."
        },
        "concept_map_nodes": [
          {"source": "Torque", "relation": "maximized_when", "target": "Force perpendicular to lever arm"},
          {"source": "Perpendicular force", "relation": "gives", "target": "τ = rF"}
        ]
      },
      "visual_system": {
        "requires_visual": false,
        "visual_type": null,
        "visual_title": null,
        "visual_description": null,
        "rendering_target": null,
        "rendering_engine": null,
        "render_width_mm": null,
        "render_height_mm": null,
        "caption": null,
        "accessibility_alt_text": null,
        "geometry_spec": null,
        "graph_spec": null,
        "table_spec": null,
        "circuit_spec": null,
        "chemistry_spec": null,
        "biology_spec": null,
        "flowchart_spec": null,
        "number_line_spec": null
      },
      "layout_metadata": {
        "page_element_type": "mcq_block",
        "suggested_placement": "main_column",
        "visual_anchor": "none",
        "box_type": "standard_mcq",
        "preceding_element": "next_mcq",
        "following_element": "next_mcq",
        "page_break_before": false,
        "keep_with_next": true,
        "column_span": 1,
        "callout_style": null,
        "heading_level": null
      },
      "publishing_metadata": {
        "target_documents": ["question_bank", "exam_paper", "workbook", "solution_manual"],
        "flashcard_deck": "Physics Unit 2 — Rotational Dynamics",
        "flashcard_front": "Find torque: 20 N perpendicular force, 0.30 m wrench.",
        "flashcard_back": "τ = rF = 0.30 × 20 = 6.0 N·m.",
        "glossary_term": "Torque",
        "glossary_definition": "Rotational effect; τ = rF when force perpendicular.",
        "revision_note": "τ = rF (perpendicular force).",
        "teacher_note": "Emphasize that torque depends on perpendicular distance from pivot.",
        "bloom_level": "Apply",
        "learning_objective_tag": "Express torque in terms of moment of inertia and angular acceleration",
        "concept_map_nodes": [
          {"source": "Torque", "relation": "formula (⊥)", "target": "τ = rF"}
        ],
        "workbook_section": "2.3 Rotational Dynamics",
        "solution_manual_note": "Answer B. τ = rF = 0.30 × 20 = 6.0 N·m."
      }
    },
    {
      "question_id": "G12_Phy_U2_Q019",
      "generation_timestamp": "2026-06-13T10:35:00Z",
      "grade": "Grade 12",
      "subject": "Physics",
      "unit": "Unit 2: Two-dimensional motion",
      "section": "2.3 Rotational Dynamics",
      "subsection": "Moment of inertia (I)",
      "sub_subsection": null,
      "structural_anchor": "Moment of inertia (I)",
      "mcq_type": "A",
      "question": "Moment of inertia is the rotational analog of what linear quantity?",
      "options": {
        "A": "Mass",
        "B": "Velocity",
        "C": "Force",
        "D": "Acceleration"
      },
      "correct_answer": "A",
      "hint": "Just as mass resists linear acceleration, moment of inertia resists angular acceleration.",
      "explanation": "Moment of inertia \\( I \\) measures an object's resistance to changes in rotational motion, analogous to mass in linear motion. In \\( \\tau = I\\alpha \\), \\( I \\) corresponds to \\( m \\) in \\( F = ma \\).",
      "difficulty_level": "easy",
      "formula_used": ["\\(\\tau = I\\alpha\\)"],
      "numeric": {
        "is_numeric": false,
        "given_values": null,
        "answer_value": null,
        "answer_unit": null,
        "calculation_steps": null,
        "significant_figures": null
      },
      "coverage": {
        "baseline": true,
        "importance_biased": false,
        "structural_element_type": "mini_heading"
      },
      "validation": {
        "no_repetition_confirmed": true,
        "length_constraints_passed": true,
        "symbol_constraints_passed": true,
        "textbook_reference_clean": true,
        "option_parallelism_score": 99,
        "explanation_validation": {
          "word_overlap_percentage": 0.0,
          "named_concept_present": true,
          "distractor_error_identified": true,
          "educational_value_score": 93
        }
      },
      "source_trace": {
        "pdf_unit": "Unit 2: Two-dimensional motion",
        "section_anchor": "2.3 Rotational Dynamics",
        "subsection_anchor": "Moment of inertia (I)",
        "structural_element": "Moment of inertia (I)",
        "content_anchor": "moment of inertia is the quantitative measure of rotational inertia, just as mass is the quantitative measure of linear inertia",
        "page_hint": 28,
        "concept_hash": "f3a5b7c9d1e3f5a7b9c1d3e5f7a9b1c3d5e7f9a1b3c5d7e9f1a3b5c7d9e1f3"
      },
      "quality_metrics": {
        "stem_complexity_score": 55,
        "distractor_quality_score": 95,
        "cognitive_level": "remembering",
        "exam_alignment_score": 92
      },
      "explanations_tiered": {
        "definition": "Moment of inertia is the measure of an object's resistance to angular acceleration.",
        "concept_summary": "Moment of inertia \\( I \\) depends on mass distribution about the axis; it plays the same role in rotation that mass plays in translation.",
        "beginner": "A heavy merry-go-round is hard to spin (large I). Light or compact objects spin easily (small I).",
        "intermediate": "In \\( \\tau = I\\alpha \\), \\( I \\) is analogous to \\( m \\) in \\( F = ma \\). Larger \\( I \\) means larger torque needed for same \\( \\alpha \\).",
        "advanced": "For a point mass, \\( I = mr^2 \\); for extended bodies, \\( I = \\sum m_i r_i^2 \\). Units: kg·m².",
        "worked_solution": [],
        "reasoning_steps": [
          "Recall Newton's second law for rotation: τ = Iα.",
          "Compare with linear: F = ma.",
          "Identical form shows I corresponds to m."
        ],
        "formula_analysis": [
          {
            "formula": "\\(\\tau = I\\alpha\\)",
            "name": "Newton's second law for rotation",
            "variables": [
              {"symbol": "\\(\\tau\\)", "meaning": "Torque", "unit": "N·m"},
              {"symbol": "\\(I\\)", "meaning": "Moment of inertia", "unit": "kg·m²"},
              {"symbol": "\\(\\alpha\\)", "meaning": "Angular acceleration", "unit": "rad/s²"}
            ],
            "derivation": "Rotational analog of F = ma."
          }
        ],
        "misconceptions": [
          "Confusing moment of inertia with torque or angular momentum.",
          "Thinking moment of inertia is the same for all axes (it depends on axis choice)."
        ],
        "related_concepts": ["Mass", "Rotational inertia", "Torque"],
        "revision_note": "I = rotational analog of mass.",
        "glossary_entry": {
          "term": "Moment of inertia",
          "definition": "Measure of rotational inertia; resistance to angular acceleration.",
          "example_equation": "\\(I = mr^2\\) (point mass)",
          "related_terms": ["Mass", "Torque", "Rotational inertia"]
        },
        "flashcard": {
          "front": "What linear quantity is moment of inertia analogous to?",
          "back": "Mass. \\( \\tau = I\\alpha \\) (rotational) is analogous to \\( F = ma \\) (linear)."
        },
        "concept_map_nodes": [
          {"source": "Moment of inertia", "relation": "analogous_to", "target": "Mass"},
          {"source": "Moment of inertia", "relation": "appears_in", "target": "\\(\\tau = I\\alpha\\)"}
        ]
      },
      "visual_system": {
        "requires_visual": false,
        "visual_type": null,
        "visual_title": null,
        "visual_description": null,
        "rendering_target": null,
        "rendering_engine": null,
        "render_width_mm": null,
        "render_height_mm": null,
        "caption": null,
        "accessibility_alt_text": null,
        "geometry_spec": null,
        "graph_spec": null,
        "table_spec": null,
        "circuit_spec": null,
        "chemistry_spec": null,
        "biology_spec": null,
        "flowchart_spec": null,
        "number_line_spec": null
      },
      "layout_metadata": {
        "page_element_type": "mcq_block",
        "suggested_placement": "main_column",
        "visual_anchor": "none",
        "box_type": "standard_mcq",
        "preceding_element": "next_mcq",
        "following_element": "next_mcq",
        "page_break_before": false,
        "keep_with_next": true,
        "column_span": 1,
        "callout_style": null,
        "heading_level": null
      },
      "publishing_metadata": {
        "target_documents": ["question_bank", "exam_paper", "flashcard_deck"],
        "flashcard_deck": "Physics Unit 2 — Rotational Dynamics",
        "flashcard_front": "What is the rotational analog of mass?",
        "flashcard_back": "Moment of inertia (I). In τ = Iα, I corresponds to m in F = ma.",
        "glossary_term": "Moment of inertia",
        "glossary_definition": "Rotational analog of mass; resistance to angular acceleration.",
        "revision_note": "I ↔ m (rotational analog).",
        "teacher_note": "Use τ = Iα vs F = ma to reinforce analogy.",
        "bloom_level": "Remember",
        "learning_objective_tag": "Define moment of inertia in terms of point mass and distance from axis",
        "concept_map_nodes": [
          {"source": "Moment of inertia", "relation": "analogous_to", "target": "Mass"}
        ],
        "workbook_section": "2.3 Rotational Dynamics",
        "solution_manual_note": "Answer A. I is rotational inertia, analogous to mass."
      }
    },
    {
      "question_id": "G12_Phy_U2_Q020",
      "generation_timestamp": "2026-06-13T10:35:00Z",
      "grade": "Grade 12",
      "subject": "Physics",
      "unit": "Unit 2: Two-dimensional motion",
      "section": "2.3 Rotational Dynamics",
      "subsection": "Moment of inertia (I)",
      "sub_subsection": null,
      "structural_anchor": "Moment of inertia (I)",
      "mcq_type": "D",
      "question": "Two point masses, \\( m_1 = 2.0 \\, \\text{kg} \\) at \\( r_1 = 0.5 \\, \\text{m} \\) and \\( m_2 = 1.0 \\, \\text{kg} \\) at \\( r_2 = 1.0 \\, \\text{m} \\), are attached to a massless rod rotating about its center. What is the moment of inertia?",
      "options": {
        "A": "\\( 0.5 \\, \\text{kg·m}^2 \\)",
        "B": "\\( 1.0 \\, \\text{kg·m}^2 \\)",
        "C": "\\( 1.5 \\, \\text{kg·m}^2 \\)",
        "D": "\\( 2.0 \\, \\text{kg·m}^2 \\)"
      },
      "correct_answer": "C",
      "hint": "For point masses, \\( I = \\sum m_i r_i^2 \\).",
      "explanation": "\\( I = m_1 r_1^2 + m_2 r_2^2 = (2.0 \\times 0.5^2) + (1.0 \\times 1.0^2) = (2.0 \\times 0.25) + 1.0 = 0.5 + 1.0 = 1.5 \\, \\text{kg·m}^2 \\). Option A omits the second mass, option B underestimates.",
      "difficulty_level": "medium",
      "formula_used": ["\\(I = \\sum m_i r_i^2\\)"],
      "numeric": {
        "is_numeric": true,
        "given_values": {
          "\\(m_1\\)": {"magnitude": 2.0, "unit": "kg"},
          "\\(r_1\\)": {"magnitude": 0.5, "unit": "m"},
          "\\(m_2\\)": {"magnitude": 1.0, "unit": "kg"},
          "\\(r_2\\)": {"magnitude": 1.0, "unit": "m"}
        },
        "answer_value": 1.5,
        "answer_unit": "kg·m²",
        "calculation_steps": [
          "I = m₁r₁² + m₂r₂²",
          "I = 2.0 × (0.5)² + 1.0 × (1.0)²",
          "I = 2.0 × 0.25 + 1.0 × 1.0",
          "I = 0.5 + 1.0 = 1.5 kg·m²"
        ],
        "significant_figures": 2
      },
      "coverage": {
        "baseline": true,
        "importance_biased": false,
        "structural_element_type": "mini_heading"
      },
      "validation": {
        "no_repetition_confirmed": true,
        "length_constraints_passed": true,
        "symbol_constraints_passed": true,
        "textbook_reference_clean": true,
        "option_parallelism_score": 96,
        "explanation_validation": {
          "word_overlap_percentage": 4.0,
          "named_concept_present": true,
          "distractor_error_identified": true,
          "educational_value_score": 94
        }
      },
      "source_trace": {
        "pdf_unit": "Unit 2: Two-dimensional motion",
        "section_anchor": "2.3 Rotational Dynamics",
        "subsection_anchor": "Moment of inertia (I)",
        "structural_element": "Moment of inertia (I)",
        "content_anchor": "I = m₁r₁² + m₂r₂² + ...",
        "page_hint": 29,
        "concept_hash": "a4b6c8d0e2f4a6b8c0d2e4f6a8b0c2d4e6f8a0b2c4d6e8f0a2b4c6d8e0f2a4"
      },
      "quality_metrics": {
        "stem_complexity_score": 68,
        "distractor_quality_score": 88,
        "cognitive_level": "apply",
        "exam_alignment_score": 93
      },
      "explanations_tiered": {
        "definition": "Moment of inertia for a system of point masses is the sum of each mass times the square of its distance from the axis.",
        "concept_summary": "Each mass contributes \\( m_i r_i^2 \\) to the total moment of inertia; farther masses contribute more because \\( r^2 \\) grows rapidly.",
        "beginner": "A mass far from the axis is harder to rotate than an equal mass near the axis — its contribution to I is larger.",
        "intermediate": "Using \\( I = \\sum m_i r_i^2 \\): \\( 2.0 \\times (0.5)^2 = 0.5 \\), \\( 1.0 \\times (1.0)^2 = 1.0 \\), sum = 1.5 kg·m².",
        "advanced": "For continuous bodies, \\( I = \\int r^2 \\, dm \\). For discrete masses, \\( I = \\sum m_i r_i^2 \\).",
        "worked_solution": [
          "Step 1: I = m₁r₁² + m₂r₂²",
          "Step 2: m₁r₁² = 2.0 × (0.5)² = 2.0 × 0.25 = 0.5 kg·m²",
          "Step 3: m₂r₂² = 1.0 × (1.0)² = 1.0 kg·m²",
          "Step 4: Total I = 0.5 + 1.0 = 1.5 kg·m²"
        ],
        "reasoning_steps": [
          "Write the formula for moment of inertia of point masses: I = Σ m_i r_i².",
          "Compute each term individually.",
          "Add the contributions."
        ],
        "formula_analysis": [
          {
            "formula": "\\(I = \\sum m_i r_i^2\\)",
            "name": "Moment of inertia for point masses",
            "variables": [
              {"symbol": "\\(I\\)", "meaning": "Moment of inertia", "unit": "kg·m²"},
              {"symbol": "\\(m_i\\)", "meaning": "Mass of i-th particle", "unit": "kg"},
              {"symbol": "\\(r_i\\)", "meaning": "Distance from axis", "unit": "m"}
            ],
            "derivation": "Definition from rotational dynamics."
          }
        ],
        "misconceptions": [
          "Using r instead of r² (linear, not squared).",
          "Forgetting to sum over all masses."
        ],
        "related_concepts": ["Rotational inertia", "Parallel axis theorem", "Point mass"],
        "revision_note": "I = Σ mᵢ rᵢ².",
        "glossary_entry": {
          "term": "Moment of inertia (discrete)",
          "definition": "Sum of mᵢrᵢ² for all point masses in a system.",
          "example_equation": "\\(I = \\sum m_i r_i^2\\)",
          "related_terms": ["Point mass", "Rotational inertia"]
        },
        "flashcard": {
          "front": "A 2 kg mass at 0.5 m and 1 kg mass at 1.0 m rotate about center. Find I.",
          "back": "I = (2)(0.5)² + (1)(1.0)² = 0.5 + 1.0 = 1.5 kg·m²."
        },
        "concept_map_nodes": [
          {"source": "Moment of inertia", "relation": "for_point_masses", "target": "\\(I = \\sum m_i r_i^2\\)"},
          {"source": "\\(I = \\sum m_i r_i^2\\)", "relation": "shows", "target": "Distance matters more (r²)"}
        ]
      },
      "visual_system": {
        "requires_visual": false,
        "visual_type": null,
        "visual_title": null,
        "visual_description": null,
        "rendering_target": null,
        "rendering_engine": null,
        "render_width_mm": null,
        "render_height_mm": null,
        "caption": null,
        "accessibility_alt_text": null,
        "geometry_spec": null,
        "graph_spec": null,
        "table_spec": null,
        "circuit_spec": null,
        "chemistry_spec": null,
        "biology_spec": null,
        "flowchart_spec": null,
        "number_line_spec": null
      },
      "layout_metadata": {
        "page_element_type": "mcq_block",
        "suggested_placement": "main_column",
        "visual_anchor": "none",
        "box_type": "standard_mcq",
        "preceding_element": "next_mcq",
        "following_element": "next_mcq",
        "page_break_before": false,
        "keep_with_next": true,
        "column_span": 1,
        "callout_style": null,
        "heading_level": null
      },
      "publishing_metadata": {
        "target_documents": ["question_bank", "exam_paper", "workbook", "solution_manual"],
        "flashcard_deck": "Physics Unit 2 — Rotational Dynamics",
        "flashcard_front": "Two masses: 2 kg at 0.5 m, 1 kg at 1.0 m from axis. Find I.",
        "flashcard_back": "I = 2(0.5)² + 1(1.0)² = 0.5 + 1.0 = 1.5 kg·m².",
        "glossary_term": "Moment of inertia",
        "glossary_definition": "I = Σ mᵢrᵢ² for point masses.",
        "revision_note": "I = Σ mr².",
        "teacher_note": "Reinforce that r is squared, so distance greatly affects I.",
        "bloom_level": "Apply",
        "learning_objective_tag": "Define moment of inertia in terms of point mass and distance from axis",
        "concept_map_nodes": [
          {"source": "Moment of inertia", "relation": "formula (discrete)", "target": "I = Σ mᵢrᵢ²"}
        ],
        "workbook_section": "2.3 Rotational Dynamics",
        "solution_manual_note": "Answer C. I = 2×(0.5)² + 1×(1.0)² = 0.5 + 1.0 = 1.5 kg·m²."
      }
    }
  ],
  "batch_metrics": {
    "generation_time_ms": 3100,
    "average_question_quality": 86.1,
    "type_distribution": {
      "A": 4,
      "C": 3,
      "D": 3
    },
    "difficulty_distribution": {
      "easy": 4,
      "medium": 6,
      "hard": 0
    },
    "section_distribution": {
      "2.2 Rotational Motion": 6,
      "2.3 Rotational Dynamics": 4
    },
    "tiered_explanation_word_counts": {
      "beginner_avg": 25,
      "intermediate_avg": 37,
      "advanced_avg": 47
    },
    "visual_required_count": 0,
    "flashcards_generated": 10,
    "glossary_terms_generated": 8
  },
  "system_checks": {
    "state_integrity_verified": true,
    "constraint_compliance": 100,
    "exhaustion_detection_active": true,
    "phase_enforcement_active": true,
    "anti_cheat_active": true,
    "tiered_explanation_system_active": true,
    "visual_system_active": true,
    "layout_system_active": true,
    "publishing_system_active": true
  }
}